{
	"1": "Itt rövid leírás olvasható a kategóriáról",
	"2": "Itt rövid leírás olvasható a kategóriáról",
	"3": "Itt rövid leírás olvasható a kategóriáról",
	"4": "Itt rövid leírás olvasható a kategóriáról",
	"5": "Itt rövid leírás olvasható a kategóriáról",
	"6": "Itt rövid leírás olvasható a kategóriáról",
	"7": "Itt rövid leírás olvasható a kategóriáról",
	"8": "Itt rövid leírás olvasható a kategóriáról",
	"9": "Itt rövid leírás olvasható a kategóriáról",
	"10": "Itt rövid leírás olvasható a kategóriáról",
	"12": "Itt rövid leírás olvasható a kategóriáról",
	"13": "Itt rövid leírás olvasható a kategóriáról",
	"14": "Itt rövid leírás olvasható a kategóriáról",
	"15": "Itt rövid leírás olvasható a kategóriáról",
	"16": "Itt rövid leírás olvasható a kategóriáról",
	"17": "Itt rövid leírás olvasható a kategóriáról",
	"18": "Itt rövid leírás olvasható a kategóriáról",
	"19": "Itt rövid leírás olvasható a kategóriáról",
	"20": "Itt rövid leírás olvasható a kategóriáról",
	"21": "Itt rövid leírás olvasható a kategóriáról",
	"22": "Itt rövid leírás olvasható a kategóriáról",
	"24": "Itt rövid leírás olvasható a kategóriáról",
	"25": "Itt rövid leírás olvasható a kategóriáról",
	"26": "Itt rövid leírás olvasható a kategóriáról",
	"27": "Itt rövid leírás olvasható a kategóriáról",
	"28": "Itt rövid leírás olvasható a kategóriáról",
	"29": "Itt rövid leírás olvasható a kategóriáról",
	"30": "Itt rövid leírás olvasható a kategóriáról",
	"31": "Itt rövid leírás olvasható a kategóriáról",
	"32": "Itt rövid leírás olvasható a kategóriáról",
	"33": "Itt rövid leírás olvasható a kategóriáról",
	"34": "Itt rövid leírás olvasható a kategóriáról",
	"35": "Itt rövid leírás olvasható a kategóriáról",
	"36": "Itt rövid leírás olvasható a kategóriáról",
	"37": "Itt rövid leírás olvasható a kategóriáról",
	"38": "Itt rövid leírás olvasható a kategóriáról",
	"39": "Itt rövid leírás olvasható a kategóriáról",
	"40": "Itt rövid leírás olvasható a kategóriáról",
	"41": "Itt rövid leírás olvasható a kategóriáról",
	"42": "Itt rövid leírás olvasható a kategóriáról",
	"43": "Itt rövid leírás olvasható a kategóriáról",
	"44": "Itt rövid leírás olvasható a kategóriáról",
	"45": "Itt rövid leírás olvasható a kategóriáról",
	"46": "Itt rövid leírás olvasható a kategóriáról",
	"47": "Itt rövid leírás olvasható a kategóriáról",
	"48": "Itt rövid leírás olvasható a kategóriáról",
	"49": "Itt rövid leírás olvasható a kategóriáról",
	"50": "Itt rövid leírás olvasható a kategóriáról",
	"52": "Itt rövid leírás olvasható a kategóriáról",
	"53": "Itt rövid leírás olvasható a kategóriáról",
	"54": "Itt rövid leírás olvasható a kategóriáról",
	"58": "Itt rövid leírás olvasható a kategóriáról",
	"59": "Itt rövid leírás olvasható a kategóriáról",
	"60": "Itt rövid leírás olvasható a kategóriáról",
	"62": "Itt rövid leírás olvasható a kategóriáról",
	"65": "Itt rövid leírás olvasható a kategóriáról",
	"67": "Itt rövid leírás olvasható a kategóriáról",
	"68": "Itt rövid leírás olvasható a kategóriáról",
	"69": "Itt rövid leírás olvasható a kategóriáról",
	"70": "Itt rövid leírás olvasható a kategóriáról",
	"71": "Itt rövid leírás olvasható a kategóriáról",
	"72": "Itt rövid leírás olvasható a kategóriáról",
	"73": "Itt rövid leírás olvasható a kategóriáról",
	"74": "Itt rövid leírás olvasható a kategóriáról",
	"79": "Itt rövid leírás olvasható a kategóriáról",
	"80": "Itt rövid leírás olvasható a kategóriáról",
	"83": "Itt rövid leírás olvasható a kategóriáról",
	"84": "Itt rövid leírás olvasható a kategóriáról",
	"89": "Itt rövid leírás olvasható a kategóriáról",
	"93": "Itt rövid leírás olvasható a kategóriáról",
	"94": "Itt rövid leírás olvasható a kategóriáról",
	"95": "Itt rövid leírás olvasható a kategóriáról",
	"97": "Itt rövid leírás olvasható a kategóriáról",
	"98": "Itt rövid leírás olvasható a kategóriáról",
	"109": "Itt rövid leírás olvasható a kategóriáról",
	"111": "Itt rövid leírás olvasható a kategóriáról",
	"113": "Itt rövid leírás olvasható a kategóriáról",
	"114": "Itt rövid leírás olvasható a kategóriáról",
	"115": "Itt rövid leírás olvasható a kategóriáról",
	"116": "Itt rövid leírás olvasható a kategóriáról",
	"117": "Itt rövid leírás olvasható a kategóriáról",
	"118": "Itt rövid leírás olvasható a kategóriáról",
	"121": "Itt rövid leírás olvasható a kategóriáról",
	"123": "Itt rövid leírás olvasható a kategóriáról",
	"124": "Itt rövid leírás olvasható a kategóriáról",
	"133": "Itt rövid leírás olvasható a kategóriáról",
	"144": "Itt rövid leírás olvasható a kategóriáról",
	"146": "Itt rövid leírás olvasható a kategóriáról",
	"160": "Itt rövid leírás olvasható a kategóriáról",
	"167": "Itt rövid leírás olvasható a kategóriáról",
	"168": "Itt rövid leírás olvasható a kategóriáról",
	"176": "Itt rövid leírás olvasható a kategóriáról",
	"177": "Itt rövid leírás olvasható a kategóriáról",
	"179": "Itt rövid leírás olvasható a kategóriáról",
	"180": "Itt rövid leírás olvasható a kategóriáról",
	"184": "Itt rövid leírás olvasható a kategóriáról",
	"186": "Itt rövid leírás olvasható a kategóriáról",
	"187": "Itt rövid leírás olvasható a kategóriáról",
	"188": "Itt rövid leírás olvasható a kategóriáról",
	"189": "Itt rövid leírás olvasható a kategóriáról",
	"190": "Itt rövid leírás olvasható a kategóriáról",
	"191": "Itt rövid leírás olvasható a kategóriáról",
	"192": "Itt rövid leírás olvasható a kategóriáról",
	"193": "Itt rövid leírás olvasható a kategóriáról",
	"195": "Itt rövid leírás olvasható a kategóriáról",
	"196": "Itt rövid leírás olvasható a kategóriáról",
	"197": "Itt rövid leírás olvasható a kategóriáról",
	"198": "Itt rövid leírás olvasható a kategóriáról",
	"200": "Itt rövid leírás olvasható a kategóriáról",
	"201": "Itt rövid leírás olvasható a kategóriáról",
	"202": "Itt rövid leírás olvasható a kategóriáról",
	"206": "Itt rövid leírás olvasható a kategóriáról",
	"209": "Itt rövid leírás olvasható a kategóriáról",
	"218": "Itt rövid leírás olvasható a kategóriáról",
	"219": "Itt rövid leírás olvasható a kategóriáról",
	"221": "Itt rövid leírás olvasható a kategóriáról",
	"222": "Itt rövid leírás olvasható a kategóriáról",
	"227": "Itt rövid leírás olvasható a kategóriáról",
	"231": "Itt rövid leírás olvasható a kategóriáról",
	"235": "Itt rövid leírás olvasható a kategóriáról",
	"237": "Itt rövid leírás olvasható a kategóriáról",
	"239": "Itt rövid leírás olvasható a kategóriáról",
	"245": "Itt rövid leírás olvasható a kategóriáról",
	"253": "Itt rövid leírás olvasható a kategóriáról",
	"257": "Itt rövid leírás olvasható a kategóriáról",
	"261": "Itt rövid leírás olvasható a kategóriáról",
	"264": "Itt rövid leírás olvasható a kategóriáról",
	"265": "Itt rövid leírás olvasható a kategóriáról",
	"283": "Itt rövid leírás olvasható a kategóriáról",
	"286": "Itt rövid leírás olvasható a kategóriáról",
	"287": "Itt rövid leírás olvasható a kategóriáról",
	"294": "Itt rövid leírás olvasható a kategóriáról",
	"296": "Itt rövid leírás olvasható a kategóriáról",
	"298": "Itt rövid leírás olvasható a kategóriáról",
	"299": "Itt rövid leírás olvasható a kategóriáról",
	"305": "Itt rövid leírás olvasható a kategóriáról",
	"307": "Itt rövid leírás olvasható a kategóriáról",
	"310": "Itt rövid leírás olvasható a kategóriáról",
	"316": "Itt rövid leírás olvasható a kategóriáról",
	"412": "Itt rövid leírás olvasható a kategóriáról",
	"421": "Itt rövid leírás olvasható a kategóriáról",
	"451": "Itt rövid leírás olvasható a kategóriáról",
	"471": "Itt rövid leírás olvasható a kategóriáról",
	"474": "Itt rövid leírás olvasható a kategóriáról",
	"510": "Itt rövid leírás olvasható a kategóriáról",
	"520": "Itt rövid leírás olvasható a kategóriáról",
	"540": "Itt rövid leírás olvasható a kategóriáról",
	"610": "Itt rövid leírás olvasható a kategóriáról",
	"630": "Itt rövid leírás olvasható a kategóriáról",
	"640": "Itt rövid leírás olvasható a kategóriáról",
	"660": "Itt rövid leírás olvasható a kategóriáról",
	"721": "Itt rövid leírás olvasható a kategóriáról",
	"722": "Itt rövid leírás olvasható a kategóriáról",
	"723": "Itt rövid leírás olvasható a kategóriáról",
	"740": "Itt rövid leírás olvasható a kategóriáról",
	"810": "Itt rövid leírás olvasható a kategóriáról",
	"820": "Itt rövid leírás olvasható a kategóriáról",
	"840": "Itt rövid leírás olvasható a kategóriáról",
	"860": "Itt rövid leírás olvasható a kategóriáról",
	"911": "Itt rövid leírás olvasható a kategóriáról",
	"912": "Itt rövid leírás olvasható a kategóriáról",
	"921": "Itt rövid leírás olvasható a kategóriáról",
	"960": "Itt rövid leírás olvasható a kategóriáról",
	"1010": "Itt rövid leírás olvasható a kategóriáról",
	"1011": "Itt rövid leírás olvasható a kategóriáról",
	"1012": "Itt rövid leírás olvasható a kategóriáról",
	"1013": "Itt rövid leírás olvasható a kategóriáról",
	"1014": "Itt rövid leírás olvasható a kategóriáról",
	"1021": "Itt rövid leírás olvasható a kategóriáról",
	"1030": "Itt rövid leírás olvasható a kategóriáról",
	"1040": "Itt rövid leírás olvasható a kategóriáról",
	"1060": "Itt rövid leírás olvasható a kategóriáról",
	"1070": "Itt rövid leírás olvasható a kategóriáról",
	"9000": "Itt rövid leírás olvasható a kategóriáról",
	"11130": "Itt rövid leírás olvasható a kategóriáról",
	"13350": "Itt rövid leírás olvasható a kategóriáról",
	"13370": "Itt rövid leírás olvasható a kategóriáról",
	"16080": "Itt rövid leírás olvasható a kategóriáról",
	"18010": "Itt rövid leírás olvasható a kategóriáról",
	"18030": "Itt rövid leírás olvasható a kategóriáról",
	"31030": "Itt rövid leírás olvasható a kategóriáról",
	"41232": "Itt rövid leírás olvasható a kategóriáról",
	"41233": "Itt rövid leírás olvasható a kategóriáról",
	"41237": "Itt rövid leírás olvasható a kategóriáról",
	"42120": "Itt rövid leírás olvasható a kategóriáról",
	"45120": "Itt rövid leírás olvasható a kategóriáról",
	"45160": "Itt rövid leírás olvasható a kategóriáról",
	"47120": "Itt rövid leírás olvasható a kategóriáról",
	"47410": "Itt rövid leírás olvasható a kategóriáról",
	"51030": "Itt rövid leírás olvasható a kategóriáról",
	"52020": "Itt rövid leírás olvasható a kategóriáról",
	"52080": "Itt rövid leírás olvasható a kategóriáról",
	"54010": "Itt rövid leírás olvasható a kategóriáról",
	"61030": "Itt rövid leírás olvasható a kategóriáról",
	"63080": "Itt rövid leírás olvasható a kategóriáról",
	"64010": "Itt rövid leírás olvasható a kategóriáról",
	"66010": "Itt rövid leírás olvasható a kategóriáról",
	"66020": "Itt rövid leírás olvasható a kategóriáról",
	"72111": "Itt rövid leírás olvasható a kategóriáról",
	"72112": "Itt rövid leírás olvasható a kategóriáról",
	"72210": "Itt rövid leírás olvasható a kategóriáról",
	"72311": "Itt rövid leírás olvasható a kategóriáról",
	"74011": "Itt rövid leírás olvasható a kategóriáról",
	"74031": "Itt rövid leírás olvasható a kategóriáról",
	"74032": "Itt rövid leírás olvasható a kategóriáról",
	"81030": "Itt rövid leírás olvasható a kategóriáról",
	"81041": "Itt rövid leírás olvasható a kategóriáról",
	"81061": "Itt rövid leírás olvasható a kategóriáról",
	"82042": "Itt rövid leírás olvasható a kategóriáról",
	"82043": "Itt rövid leírás olvasható a kategóriáról",
	"82044": "Itt rövid leírás olvasható a kategóriáról",
	"82091": "Itt rövid leírás olvasható a kategóriáról",
	"84031": "Itt rövid leírás olvasható a kategóriáról",
	"84040": "Itt rövid leírás olvasható a kategóriáról",
	"86010": "Itt rövid leírás olvasható a kategóriáról",
	"86020": "Itt rövid leírás olvasható a kategóriáról",
	"86030": "Itt rövid leírás olvasható a kategóriáról",
	"86090": "Itt rövid leírás olvasható a kategóriáról",
	"91140": "Itt rövid leírás olvasható a kategóriáról",
	"91220": "Itt rövid leírás olvasható a kategóriáról",
	"91250": "Itt rövid leírás olvasható a kategóriáról",
	"92120": "Itt rövid leírás olvasható a kategóriáról",
	"96015": "Itt rövid leírás olvasható a kategóriáról",
	"101150": "Itt rövid leírás olvasható a kategóriáról",
	"104042": "Itt rövid leírás olvasható a kategóriáról",
	"104051": "Itt rövid leírás olvasható a kategóriáról",
	"106020": "Itt rövid leírás olvasható a kategóriáról",
	"107060": "Itt rövid leírás olvasható a kategóriáról",
	"900020": "Itt rövid leírás olvasható a kategóriáról",
	"undefined": "Itt rövid leírás olvasható a kategóriáról",
	"K1": "Itt rövid leírás olvasható a kategóriáról",
	"K11": "Itt rövid leírás olvasható a kategóriáról",
	"K1101": "Itt rövid leírás olvasható a kategóriáról",
	"K1104": "Itt rövid leírás olvasható a kategóriáról",
	"K1107": "Itt rövid leírás olvasható a kategóriáról",
	"K1109": "Itt rövid leírás olvasható a kategóriáról",
	"K1110": "Itt rövid leírás olvasható a kategóriáról",
	"K1113": "Itt rövid leírás olvasható a kategóriáról",
	"K12": "Itt rövid leírás olvasható a kategóriáról",
	"K121": "Itt rövid leírás olvasható a kategóriáról",
	"K122": "Itt rövid leírás olvasható a kategóriáról",
	"K123": "Itt rövid leírás olvasható a kategóriáról",
	"K2": "Itt rövid leírás olvasható a kategóriáról",
	"K3": "Itt rövid leírás olvasható a kategóriáról",
	"K31": "Itt rövid leírás olvasható a kategóriáról",
	"K311": "Itt rövid leírás olvasható a kategóriáról",
	"K312": "Itt rövid leírás olvasható a kategóriáról",
	"K32": "Itt rövid leírás olvasható a kategóriáról",
	"K321": "Itt rövid leírás olvasható a kategóriáról",
	"K322": "Itt rövid leírás olvasható a kategóriáról",
	"K33": "Itt rövid leírás olvasható a kategóriáról",
	"K331": "Itt rövid leírás olvasható a kategóriáról",
	"K332": "Itt rövid leírás olvasható a kategóriáról",
	"K333": "Itt rövid leírás olvasható a kategóriáról",
	"K334": "Itt rövid leírás olvasható a kategóriáról",
	"K335": "Itt rövid leírás olvasható a kategóriáról",
	"K336": "Itt rövid leírás olvasható a kategóriáról",
	"K337": "Itt rövid leírás olvasható a kategóriáról",
	"K34": "Itt rövid leírás olvasható a kategóriáról",
	"K341": "Itt rövid leírás olvasható a kategóriáról",
	"K342": "Itt rövid leírás olvasható a kategóriáról",
	"K35": "Itt rövid leírás olvasható a kategóriáról",
	"K351": "Itt rövid leírás olvasható a kategóriáról",
	"K352": "Itt rövid leírás olvasható a kategóriáról",
	"K355": "Itt rövid leírás olvasható a kategóriáról",
	"K4": "Itt rövid leírás olvasható a kategóriáról",
	"K42": "Itt rövid leírás olvasható a kategóriáról",
	"K47": "Itt rövid leírás olvasható a kategóriáról",
	"K48": "Itt rövid leírás olvasható a kategóriáról",
	"K5": "Itt rövid leírás olvasható a kategóriáról",
	"K502": "Itt rövid leírás olvasható a kategóriáról",
	"K5021": "Itt rövid leírás olvasható a kategóriáról",
	"K512": "Itt rövid leírás olvasható a kategóriáról",
	"K6": "Itt rövid leírás olvasható a kategóriáról",
	"K62": "Itt rövid leírás olvasható a kategóriáról",
	"K63": "Itt rövid leírás olvasható a kategóriáról",
	"K64": "Itt rövid leírás olvasható a kategóriáról",
	"K67": "Itt rövid leírás olvasható a kategóriáról",
	"K7": "Itt rövid leírás olvasható a kategóriáról",
	"K71": "Itt rövid leírás olvasható a kategóriáról",
	"K73": "Itt rövid leírás olvasható a kategóriáról",
	"K74": "Itt rövid leírás olvasható a kategóriáról",
	"K8": "Itt rövid leírás olvasható a kategóriáról",
	"K85": "Itt rövid leírás olvasható a kategóriáról",
	"K9": "Itt rövid leírás olvasható a kategóriáról",
	"K91": "Itt rövid leírás olvasható a kategóriáról",
	"K914": "Itt rövid leírás olvasható a kategóriáról",
	"K915": "Itt rövid leírás olvasható a kategóriáról",
	"B1": "Itt rövid leírás olvasható a kategóriáról",
	"B11": "Itt rövid leírás olvasható a kategóriáról",
	"B111": "Itt rövid leírás olvasható a kategóriáról",
	"B112": "Itt rövid leírás olvasható a kategóriáról",
	"B113": "Itt rövid leírás olvasható a kategóriáról",
	"B114": "Itt rövid leírás olvasható a kategóriáról",
	"B115": "Itt rövid leírás olvasható a kategóriáról",
	"B116": "Itt rövid leírás olvasható a kategóriáról",
	"B16": "Itt rövid leírás olvasható a kategóriáról",
	"B2": "Itt rövid leírás olvasható a kategóriáról",
	"B21": "Itt rövid leírás olvasható a kategóriáról",
	"B25": "Itt rövid leírás olvasható a kategóriáról",
	"B3": "Itt rövid leírás olvasható a kategóriáról",
	"B31": "Itt rövid leírás olvasható a kategóriáról",
	"B311": "Itt rövid leírás olvasható a kategóriáról",
	"B34": "Itt rövid leírás olvasható a kategóriáról",
	"B35": "Itt rövid leírás olvasható a kategóriáról",
	"B351": "Itt rövid leírás olvasható a kategóriáról",
	"B354": "Itt rövid leírás olvasható a kategóriáról",
	"B36": "Itt rövid leírás olvasható a kategóriáról",
	"B4": "Itt rövid leírás olvasható a kategóriáról",
	"B401": "Itt rövid leírás olvasható a kategóriáról",
	"B402": "Itt rövid leírás olvasható a kategóriáról",
	"B403": "Itt rövid leírás olvasható a kategóriáról",
	"B404": "Itt rövid leírás olvasható a kategóriáról",
	"B405": "Itt rövid leírás olvasható a kategóriáról",
	"B406": "Itt rövid leírás olvasható a kategóriáról",
	"B408": "Itt rövid leírás olvasható a kategóriáról",
	"B4082": "Itt rövid leírás olvasható a kategóriáról",
	"B410": "Itt rövid leírás olvasható a kategóriáról",
	"B411": "Itt rövid leírás olvasható a kategóriáról",
	"B5": "Itt rövid leírás olvasható a kategóriáról",
	"B53": "Itt rövid leírás olvasható a kategóriáról",
	"B6": "Itt rövid leírás olvasható a kategóriáról",
	"B64": "Itt rövid leírás olvasható a kategóriáról",
	"B65": "Itt rövid leírás olvasható a kategóriáról",
	"B7": "Itt rövid leírás olvasható a kategóriáról",
	"B74": "Itt rövid leírás olvasható a kategóriáról",
	"B8": "Itt rövid leírás olvasható a kategóriáról",
	"B81": "Itt rövid leírás olvasható a kategóriáról",
	"B813": "Itt rövid leírás olvasható a kategóriáról",
	"B8131": "Itt rövid leírás olvasható a kategóriáról",
	"B814": "Itt rövid leírás olvasható a kategóriáról",
	"K1103": "Itt rövid leírás olvasható a kategóriáról",
	"K513": "Itt rövid leírás olvasható a kategóriáról"
}